isogeo_xml_toolbelt/__about__.py
isogeo_xml_toolbelt/__init__.py
isogeo_xml_toolbelt/md_xml_fixer.py
isogeo_xml_toolbelt/switch_from_geosource.py
isogeo_xml_toolbelt/enums/__init__.py
isogeo_xml_toolbelt/models/__init__.py
isogeo_xml_toolbelt/models/xml_19139_fields.py
isogeo_xml_toolbelt/readers/__init__.py
isogeo_xml_toolbelt/readers/reader_iso19110.py
isogeo_xml_toolbelt/readers/reader_iso19139.py
isogeo_xml_toolbelt/reporters/__init__.py
isogeo_xml_toolbelt/reporters/csv_reporter.py
isogeo_xml_toolbelt/utils/__init__.py
isogeo_xml_toolbelt/utils/xml_utils.py
isogeo_xml_toolbelt-1.0.0.dist-info/LICENSE
isogeo_xml_toolbelt-1.0.0.dist-info/METADATA
isogeo_xml_toolbelt-1.0.0.dist-info/WHEEL
isogeo_xml_toolbelt-1.0.0.dist-info/top_level.txt
isogeo_xml_toolbelt-1.0.0.dist-info/RECORD
