Metadata-Version: 2.1
Name: isogeo-xml-toolbelt
Version: 1.0.0
Summary: Toolbelt to read, import and export metadata stored in XML according to the ISO standards 19139 and 19110.
Home-page: https://github.com/isogeo/xml-toolbelt-py/
Author: Isogeo
Author-email: support@isogeo.com
License: LGPL3
Project-URL: Docs, https://isogeo-xml-toolbelt.readthedocs.io/
Project-URL: Bug Reports, https://github.com/isogeo/xml-toolbelt-py/issues/
Project-URL: Source, https://github.com/isogeo/xml-toolbelt-py/
Keywords: GIS metadata INSPIRE Isogeo API REST geographical data ISO19139 XML geonetwork
Platform: UNKNOWN
Classifier: Intended Audience :: Developers
Classifier: Intended Audience :: Information Technology
Classifier: Programming Language :: Python :: 3
Classifier: Programming Language :: Python :: 3.6
Classifier: Programming Language :: Python :: 3.7
Classifier: Development Status :: 5 - Production/Stable
Classifier: License :: OSI Approved :: GNU General Public License v3 (GPLv3)
Classifier: Operating System :: OS Independent
Classifier: Topic :: Software Development :: Libraries :: Python Modules
Requires-Python: >=3.6, <4
Requires-Dist: lxml (==4.4.*)
Provides-Extra: dev
Requires-Dist: black ; extra == 'dev'
Requires-Dist: python-dotenv ; extra == 'dev'
Provides-Extra: test
Requires-Dist: codecov ; extra == 'test'
Requires-Dist: coverage ; extra == 'test'
Requires-Dist: pytest ; extra == 'test'
Requires-Dist: pytest-cov ; extra == 'test'
